LICENSE.txt
setup.py
WesamCul.egg-info/PKG-INFO
WesamCul.egg-info/SOURCES.txt
WesamCul.egg-info/dependency_links.txt
WesamCul.egg-info/top_level.txt
code/__init__.py